.appveyor.yml
.gitignore
.pylintrc
.style.yapf
.travis.yml
LICENSE
MANIFEST.in
Makefile
README.md
constraints.txt
requirements.txt
setup.py
tox.ini
requirements/dev.txt
requirements/install_requires.txt
requirements/tox.txt
samples/great_and_small.py
samples/mumbo_jumbo.json
samples/nesbitt.sh
samples/short_and_squat.py
samples/spruce.json
samples/nested_directory/argle_bargle.json
src/xfmt/__init__.py
src/xfmt/base.py
src/xfmt/black_fmt.py
src/xfmt/cli.py
src/xfmt/json_fmt.py
src/xfmt/misc.py
src/xfmt.egg-info/PKG-INFO
src/xfmt.egg-info/SOURCES.txt
src/xfmt.egg-info/dependency_links.txt
src/xfmt.egg-info/entry_points.txt
src/xfmt.egg-info/requires.txt
src/xfmt.egg-info/top_level.txt
tests/__init__.py
tests/test_xfmt.py