Metadata-Version: 2.1
Name: xfmt
Version: 0.1.1
Summary: Universal formatter
Home-page: https://github.com/apljungquist/xfmt
Author: AP Ljungquist
Author-email: ap@ljungquist.eu
License: UNKNOWN
Platform: UNKNOWN
Classifier: Development Status :: 3 - Alpha
Classifier: Programming Language :: Python :: 3
Classifier: License :: OSI Approved :: MIT License
Classifier: Operating System :: OS Independent
